eNMRpy/MOSY.py
eNMRpy/Phasefitting.py
eNMRpy/__init__.py
eNMRpy/tools.py
eNMRpy/Measurement/Emma.py
eNMRpy/Measurement/Flo.py
eNMRpy/Measurement/Juergen1.py
eNMRpy/Measurement/Pavel.py
eNMRpy/Measurement/Simulated.py
eNMRpy/Measurement/__init__.py
eNMRpy/Measurement/base.py
eNMRpy/Measurement/eNMR_Methods.py
eNMRpy/Measurement/tools.py
eNMRpy-0.0.6.dist-info/LICENCE.txt
eNMRpy-0.0.6.dist-info/METADATA
eNMRpy-0.0.6.dist-info/WHEEL
eNMRpy-0.0.6.dist-info/top_level.txt
eNMRpy-0.0.6.dist-info/RECORD
