Metadata-Version: 2.1
Name: eNMRpy
Version: 0.0.6
Summary: nmrglue-based package for the import and analysis of electrophoretic NMR-data
Home-page: https://github.com/Flackermann/eNMRpy/
Author: Florian Ackermann
Author-email: nairolf.ackermann@gmail.com
License: LICENSE.txt
Platform: UNKNOWN
Requires-Dist: nmrglue
Requires-Dist: lmfit (>=1.0.1)
Requires-Dist: pandas
Requires-Dist: matplotlib (>=3.1.3)
Requires-Dist: numpy
Requires-Dist: scipy
Requires-Dist: scikit-learn (<=0.23)
